swarm_iot/__init__.py
swarm_iot/cli.py
swarm_iot/swarm_iot.py
swarm_iot-0.1.0.dist-info/AUTHORS.rst
swarm_iot-0.1.0.dist-info/LICENSE
swarm_iot-0.1.0.dist-info/METADATA
swarm_iot-0.1.0.dist-info/WHEEL
swarm_iot-0.1.0.dist-info/entry_points.txt
swarm_iot-0.1.0.dist-info/top_level.txt
swarm_iot-0.1.0.dist-info/RECORD
