Metadata-Version: 2.1
Name: swarm-iot
Version: 0.1.0
Summary: IoT as a decentralized Swarm
Home-page: https://github.com/asteriogonzalez/swarm_iot
Author: Asterio
Author-email: asterio.gonzalez@gmail.com
License: MIT license
Keywords: swarm_iot
Classifier: Development Status :: 2 - Pre-Alpha
Classifier: Intended Audience :: Developers
Classifier: License :: OSI Approved :: MIT License
Classifier: Natural Language :: English
Classifier: Programming Language :: Python :: 3
Classifier: Programming Language :: Python :: 3.6
Classifier: Programming Language :: Python :: 3.7
Classifier: Programming Language :: Python :: 3.8
Requires-Python: >=3.6
License-File: LICENSE
License-File: AUTHORS.rst
Requires-Dist: Click (>=7.0)
